welcomer/__init__.py
welcometomycourse/__init__.py
welcometomycourse-0.0.1.dist-info/METADATA
welcometomycourse-0.0.1.dist-info/WHEEL
welcometomycourse-0.0.1.dist-info/top_level.txt
welcometomycourse-0.0.1.dist-info/RECORD
